{
  "-MYqJFS0ZweVrORPnSKg": {
    "block": "data:\nblock-nr: 0\nprev-hash: 0000000000000000000000000000000000000000000000000000000000000000\ntransactions:\ncoinbase: 99999\ntimestamp: April 21, 2021 at 11:20:37 PM GMT+2\nnonce: 15544982",
    "blockNr": 0,
    "coinbase": "99999",
    "hash": "0000009bf758d277a3164e09be2026b1179d99d55461af5e4c432289b3c9335d",
    "knownWalletsWithBalances": [
      {
        "balance": 50,
        "wallet": "99999"
      }
    ],
    "miner": "Satoshi Nakamoto",
    "nonce": 15544982,
    "previousHash": "0000000000000000000000000000000000000000000000000000000000000000",
    "timestamp": 1619040186023
  },
  "-MYqafg-POxj1kD4vNoL": {
    "block": "data:\nblock-nr: 1\nprev-hash: 0000009bf758d277a3164e09be2026b1179d99d55461af5e4c432289b3c9335d\ntransactions:\n99999 -> 22446 | 21b73b22 (1 BTC) @ 1619044403116\n99999 -> 24796 | 5a87664e (1 BTC) @ 1619044434498\n99999 -> 25290 | ce90ec6f (1 BTC) @ 1619044446839\n99999 -> 27200 | 1ad54569 (1 BTC) @ 1619044452353\n99999 -> 27734 | c8c2fafd (1 BTC) @ 1619044458906\n99999 -> 29734 | b31d2676 (1 BTC) @ 1619044463990\n99999 -> 31464 | e1b102d1 (1 BTC) @ 1619044472058\n99999 -> 33646 | 022d9509 (1 BTC) @ 1619044477771\n99999 -> 35068 | 0109fcae (1 BTC) @ 1619044485481\n99999 -> 35908 | c6ade41c (1 BTC) @ 1619044490385\n99999 -> 38068 | 51ef5f33 (1 BTC) @ 1619044494984\n99999 -> 40352 | 7d042de1 (1 BTC) @ 1619044501945\n99999 -> 41464 | 044cd5e9 (1 BTC) @ 1619044507036\n99999 -> 42130 | 7fbdacc1 (1 BTC) @ 1619044512111\ncoinbase: 99999\ntimestamp: April 21, 2021 at 11:34:03 PM\nnonce: 7114613",
    "blockNr": 1,
    "coinbase": "99999",
    "hash": "0000002e925f0a45e56cfbba524ab801cb48b0149bd7bf7625b430c1ba70a2e9",
    "knownWalletsWithBalances": [
      {
        "balance": 1,
        "wallet": "22446"
      },
      {
        "balance": 1,
        "wallet": "24796"
      },
      {
        "balance": 1,
        "wallet": "25290"
      },
      {
        "balance": 1,
        "wallet": "27200"
      },
      {
        "balance": 1,
        "wallet": "27734"
      },
      {
        "balance": 1,
        "wallet": "29734"
      },
      {
        "balance": 1,
        "wallet": "31464"
      },
      {
        "balance": 1,
        "wallet": "33646"
      },
      {
        "balance": 1,
        "wallet": "35068"
      },
      {
        "balance": 1,
        "wallet": "35908"
      },
      {
        "balance": 1,
        "wallet": "38068"
      },
      {
        "balance": 1,
        "wallet": "40352"
      },
      {
        "balance": 1,
        "wallet": "41464"
      },
      {
        "balance": 1,
        "wallet": "42130"
      },
      {
        "balance": 37,
        "wallet": "99999"
      }
    ],
    "miner": "Satoshi Nakamoto",
    "nonce": 7114613,
    "previousHash": "0000009bf758d277a3164e09be2026b1179d99d55461af5e4c432289b3c9335d",
    "timestamp": 1619041990135,
    "transactions": [
      {
        "amount": 1,
        "owner": "1e864139-c486-4372-aad6-623642fc855c",
        "recipient": 22446,
        "sender": 99999,
        "signature": "21b73b22",
        "timestamp": 1619044403116
      },
      {
        "amount": 1,
        "owner": "2052b9c1-7fa3-4451-9452-203b3ef1df8a",
        "recipient": 24796,
        "sender": 99999,
        "signature": "5a87664e",
        "timestamp": 1619044434498
      },
      {
        "amount": 1,
        "owner": "2052b9c1-7fa3-4451-9452-203b3ef1df8a",
        "recipient": 25290,
        "sender": 99999,
        "signature": "ce90ec6f",
        "timestamp": 1619044446839
      },
      {
        "amount": 1,
        "owner": "2052b9c1-7fa3-4451-9452-203b3ef1df8a",
        "recipient": 27200,
        "sender": 99999,
        "signature": "1ad54569",
        "timestamp": 1619044452353
      },
      {
        "amount": 1,
        "owner": "2052b9c1-7fa3-4451-9452-203b3ef1df8a",
        "recipient": 27734,
        "sender": 99999,
        "signature": "c8c2fafd",
        "timestamp": 1619044458906
      },
      {
        "amount": 1,
        "owner": "2052b9c1-7fa3-4451-9452-203b3ef1df8a",
        "recipient": 29734,
        "sender": 99999,
        "signature": "b31d2676",
        "timestamp": 1619044463990
      },
      {
        "amount": 1,
        "owner": "2052b9c1-7fa3-4451-9452-203b3ef1df8a",
        "recipient": 31464,
        "sender": 99999,
        "signature": "e1b102d1",
        "timestamp": 1619044472058
      },
      {
        "amount": 1,
        "owner": "2052b9c1-7fa3-4451-9452-203b3ef1df8a",
        "recipient": 33646,
        "sender": 99999,
        "signature": "022d9509",
        "timestamp": 1619044477771
      },
      {
        "amount": 1,
        "owner": "2052b9c1-7fa3-4451-9452-203b3ef1df8a",
        "recipient": 35068,
        "sender": 99999,
        "signature": "0109fcae",
        "timestamp": 1619044485481
      },
      {
        "amount": 1,
        "owner": "2052b9c1-7fa3-4451-9452-203b3ef1df8a",
        "recipient": 35908,
        "sender": 99999,
        "signature": "c6ade41c",
        "timestamp": 1619044490385
      },
      {
        "amount": 1,
        "owner": "2052b9c1-7fa3-4451-9452-203b3ef1df8a",
        "recipient": 38068,
        "sender": 99999,
        "signature": "51ef5f33",
        "timestamp": 1619044494984
      },
      {
        "amount": 1,
        "owner": "2052b9c1-7fa3-4451-9452-203b3ef1df8a",
        "recipient": 40352,
        "sender": 99999,
        "signature": "7d042de1",
        "timestamp": 1619044501945
      },
      {
        "amount": 1,
        "owner": "2052b9c1-7fa3-4451-9452-203b3ef1df8a",
        "recipient": 41464,
        "sender": 99999,
        "signature": "044cd5e9",
        "timestamp": 1619044507036
      },
      {
        "amount": 1,
        "owner": "2052b9c1-7fa3-4451-9452-203b3ef1df8a",
        "recipient": 42130,
        "sender": 99999,
        "signature": "7fbdacc1",
        "timestamp": 1619044512111
      }
    ]
  }
}
